libname/__init__.py
libname/hello.py
hellorynepkg-0.0.9.dist-info/METADATA
hellorynepkg-0.0.9.dist-info/WHEEL
hellorynepkg-0.0.9.dist-info/top_level.txt
hellorynepkg-0.0.9.dist-info/RECORD
