Metadata-Version: 2.1
Name: hellorynepkg
Version: 0.0.9
Summary: The test
Home-page: UNKNOWN
Author: dannyJack (Daniel Cisneros)
Author-email: <work.dcisneros@gmail.com>
License: UNKNOWN
Keywords: python
Platform: UNKNOWN
Classifier: Development Status :: 1 - Planning
Classifier: Intended Audience :: Developers
Classifier: Programming Language :: Python :: 3
Classifier: Operating System :: Unix
Classifier: Operating System :: MacOS :: MacOS X
Classifier: Operating System :: Microsoft :: Windows
